setup.py
esvalues/__init__.py
esvalues/esvalues.py
esvalues/iterators.py
esvalues.egg-info/PKG-INFO
esvalues.egg-info/SOURCES.txt
esvalues.egg-info/dependency_links.txt
esvalues.egg-info/not-zip-safe
esvalues.egg-info/requires.txt
esvalues.egg-info/top_level.txt