Metadata-Version: 1.0
Name: esvalues
Version: 0.4
Summary: Estimates Expectation Shapley (ES) values for arbirary functions.
Home-page: http://github.com/interpretable-ml/esvalues.py
Author: Scott Lundberg
Author-email: slund1@cs.washington.edu
License: MIT
Platform: UNKNOWN
